Workbook

Sheet  Ganado bovino
B2: Cría de ganado bovino
B3: Cuadro de oferta y utilización - COU -
B4: Millones de quetzales
B5: Año 2023 p/
B7: Cuadrante de la oferta | G7: Cuadrante de la utilización
B9: Código NPG 2/ | C9: Producto | D9: Monto | G9: Código NPG 2/ | H9: Producto | I9: Monto
B10: P021 | C10: =[2]Catálogo!F27 -> Ganado bovino | D10: 6992.0263 | G10: P011 | H10: =[2]Catálogo!F17 -> Tabaco y otras plantas no perennes | I10: 762.91318
B11: P024 | C11: =[2]Catálogo!F30 -> Leche cruda | D11: 2923.5241 | G11: P026 | H11: =[2]Catálogo!F32 -> Otros productos de animales vivos | I11: 81.884613
B12: P096 | C12: =[2]Catálogo!F102 -> Agua natural y distribución de agua natural | D12: 7.138217 | G12: P033 | H12: =[2]Catálogo!F39 -> Minerales no metálicos | I12: 28.740701
B13: Ajuste CIF/FOB | D13: 0 | G13: P052 | H13: =[2]Catálogo!F58 -> Azúcar de caña sin refinar y refinada, melaza y los demás azúcares n.c.p. | I13: 66.707651
B14: Total | D14: 9922.6885 | G14: P054 | H14: =[2]Catálogo!F60 -> Preparados para alimentación animal | I14: 1504.0161
B15: Fuente: Banco de Guatemala | G15: P059 | H15: =[2]Catálogo!F65 -> Hilados, tejidos, telas y otros productos textiles excepto prendas de vestir | I15: 2.7530273
B16: p/ Cifras preliminares | G16: P060 | H16: =[2]Catálogo!F66 -> Prendas de vestir, adobo y teñido de pieles | I16: 3.1127914
B17: Nota: | G17: P064 | H17: =[2]Catálogo!F70 -> Pasta de papel y papel | I17: 16.919841
B18: CIF | C18: Costo, seguro y flete | G18: P065 | H18: =[2]Catálogo!F71 -> Envases de papel y cartón | I18: 1.8822766
B19: FOB | C19: Libre a bordo | G19: P068 | H19: =[2]Catálogo!F74 -> Gasolinas, diésel oil y fuel oils | I19: 60.334588
G20: P069 | H20: =[2]Catálogo!F75 -> Aceites, grasas lubricantes y otros aceites preparados | I20: 11.925359
G21: P071 | H21: =[2]Catálogo!F77 -> Abonos, fertilizantes y pesticidas | I21: 81.015396
G22: P073 | H22: =[2]Catálogo!F79 -> Jabón, preparados de limpieza, perfumes y preparados de toilet | I22: 6.6480512
G23: P074 | H23: =[2]Catálogo!F80 -> Otros productos químicos | I23: 0.3690561
G24: P075 | H24: =[2]Catálogo!F81 -> Productos farmacéuticos | I24: 555.24384
B25: Valor Agregado | G25: P084 | H25: =[2]Catálogo!F90 -> Otros productos elaborados de metal | I25: 9.7954063
G26: P091 | H26: =[2]Catálogo!F97 -> Equipo de transporte | I26: 7.9778743
B27: B1b | C27: Valor agregado bruto total / PIB | D27: 5822.6853 | G27: P093 | H27: =[2]Catálogo!F99 -> Otros artículos n.c.p. | I27: 21.251734
B28: D1 | C28: Remuneración de los asalariados | D28: 1765.7669 | G28: P094 | H28: =[2]Catálogo!F100 -> Residuos y desechos | I28: 515.96369
B29: D11 | C29: Sueldos y salarios | D29: 1708.8491 | G29: P095 | H29: =[2]Catálogo!F101 -> Generación y distribución de energía eléctrica, gas, vapor y aire acondicionado | I29: 28.334796
B30: D12 | C30: Contribuciones sociales de los empleadores | D30: 56.917798 | G30: P096 | H30: =[2]Catálogo!F102 -> Agua natural y distribución de agua natural | I30: 7.1397384
B31: D29 | C31: Otros impuestos sobre la producción | D31: 20.37409 | G31: P101 | H31: =[2]Catálogo!F107 -> Servicios generales y especializados de construcción | I31: 29.58536
B32: D39 | C32: Otras subvenciones a la producción | D32: 0 | G32: P103 | H32: =[2]Catálogo!F109 -> Mantenimiento y reparación de vehículos automotores y motocicletas | I32: 5.3559498
B33: B2b | C33: Excedente de explotación, bruto | D33: 1594.3075 | G33: P105 | H33: =[2]Catálogo!F111 -> Servicio de transporte de carga por vía terrestre | I33: 7.3488775
B34: B3b | C34: Ingreso mixto, bruto | D34: 2442.2368 | G34: P110 | H34: =[2]Catálogo!F116 -> Servicio de alojamiento | I34: 1.6734592
B35: Fuente: Banco de Guatemala | G35: P111 | H35: =[2]Catálogo!F117 -> Servicio de suministro de comidas y bebidas | I35: 2.7970873
B36: p/ Cifras preliminares | G36: P112 | H36: =[2]Catálogo!F118 -> Servicios de información, telecomunicaciones y radiodifusión | I36: 11.788413
G37: P114 | H37: =[2]Catálogo!F120 -> Otros servicios financieros y servicios de banca de inversión | I37: 1.2705212
C38: Puestos de Trabajo | D38: 98008 | G38: P115 | H38: =[2]Catálogo!F121 -> Servicios de Intermediación Financiera Medidos Indirectamente (SIFMI) | I38: 53.071997
B39: Fuente: Banco de Guatemala | G39: P116 | H39: =[2]Catálogo!F122 -> Servicios de seguro, reaseguro y fondos de pensiones | I39: 2.604242
B40: p/ Cifras preliminares | G40: P119 | H40: =[2]Catálogo!F125 -> Otros servicios inmobiliarios, excepto alquiler de vivienda | I40: 4.4253514
G41: P120 | H41: =[2]Catálogo!F126 -> Servicios jurídicos, de contabilidad, auditoría, teneduría de libros y consultoría fiscal | I41: 33.126804
G42: P123 | H42: =[2]Catálogo!F129 -> Otros servicios profesionales, científicos y técnicos | I42: 76.583302
G43: P125 | H43: =[2]Catálogo!F131 -> Servicios de arrendamiento o alquiler sin operador | I43: 12.800119
G44: P126 | H44: =[2]Catálogo!F132 -> Servicios de agencias de empleo y de dotación de recursos humanos | I44: 2.4664604
G45: P128 | H45: =[2]Catálogo!F134 -> Servicios de seguridad, sistemas de seguridad e investigación privada | I45: 23.883323
G46: P132 | H46: =[2]Catálogo!F138 -> Servicios de mantenimiento, reparación e instalación de productos metálicos elaborados, maquinaria y equipo | I46: 16.158635
G47: P134 | H47: =[2]Catálogo!F140 -> Servicios de apoyo a la agricultura, caza, silvicultura y pesca | I47: 6.1775737
G48: P147 | H48: =[2]Catálogo!F153 -> Servicios de asociaciones que sirven a las empresas | I48: 33.956056
G49: Total | I49: 8395.5217
G50: Fuente: Banco de Guatemala
G51: 2/ Nomenclatura de Productos para Guatemala
G52: p/ Cifras preliminares

Sheet  Ganado bovino (oferta)
B2: Tabla 1
B3: Guatemala: Cría de ganado bovino, excepto búfalos
B4: Cuadrante de la oferta del COU
B5: Millones de quetzales y porcentaje
B6: Año 2023 p/
B8: Ranking | C8: Código NPG 2/ | D8: Producto | E8: Monto | F8: Participación (%)
B9: 1 | C9: P021 | D9: =[2]Catálogo!F27 -> Ganado bovino | E9: 6992.0263 | F9: =E9/$E$13*100 -> 70.465038
B10: =B9+1 -> 2 | C10: P024 | D10: Leche cruda | E10: 2923.5241 | F10: =E10/$E$13*100 -> 29.463023
B11: =B10+1 -> 3 | C11: P096 | D11: Agua natural y distribución de agua natural | E11: 7.138217 | F11: =E11/$E$13*100 -> 0.071938335
B12: Ajuste CIF/FOB | E12: 0
B13: Total | E13: 9922.6885 | F13: =SUM(F9:F11) -> 100
B14: Fuente: Elaboración propia a partir de datos del Banco de Guatemala
B15: p/ Cifras preliminares
B16: Nota:
B17: CIF | D17: Costo, seguro y flete
B18: FOB | D18: Libre a bordo

Sheet  Ganado bovino (demanda)
B2: Cría de ganado bovino
B3: Cuadro de oferta y utilización - COU -
B4: Millones de quetzales
B5: Año 2023 p/
B7: Cuadrante de la utilización
B9: Ranking | C9: Código NPG 2/ | D9: Producto | E9: Monto | F9: Participación (%)
C10: P011 | D10: =[2]Catálogo!F17 -> Tabaco y otras plantas no perennes | E10: 762.91318 | F10: =E10/$E$49*100 -> 18.607624
C11: P026 | D11: =[2]Catálogo!F32 -> Otros productos de animales vivos | E11: 81.884613 | F11: =E11/$E$49*100 -> 1.9971841
C12: P033 | D12: =[2]Catálogo!F39 -> Minerales no metálicos | E12: 28.740701 | F12: =E12/$E$49*100 -> 0.70099215
C13: P052 | D13: =[2]Catálogo!F58 -> Azúcar de caña sin refinar y refinada, melaza y los demás azúcares n.c.p. | E13: 66.707651 | F13: =E13/$E$49*100 -> 1.6270146
C14: P054 | D14: =[2]Catálogo!F60 -> Preparados para alimentación animal | E14: 1504.0161 | F14: =E14/$E$49*100 -> 36.68329
C15: P059 | D15: =[2]Catálogo!F65 -> Hilados, tejidos, telas y otros productos textiles excepto prendas de vestir | E15: 2.7530273 | F15: =E15/$E$49*100 -> 0.067146953
C16: P060 | D16: =[2]Catálogo!F66 -> Prendas de vestir, adobo y teñido de pieles | E16: 3.1127914 | F16: =E16/$E$49*100 -> 0.075921681
C17: P064 | D17: =[2]Catálogo!F70 -> Pasta de papel y papel | E17: 16.919841 | F17: =E17/$E$49*100 -> 0.41267873
C18: P065 | D18: =[2]Catálogo!F71 -> Envases de papel y cartón | E18: 1.8822766 | F18: =E18/$E$49*100 -> 0.04590915
C19: P068 | D19: =[2]Catálogo!F74 -> Gasolinas, diésel oil y fuel oils | E19: 60.334588 | F19: =E19/$E$49*100 -> 1.4715742
C20: P069 | D20: =[2]Catálogo!F75 -> Aceites, grasas lubricantes y otros aceites preparados | E20: 11.925359 | F20: =E20/$E$49*100 -> 0.29086218
C21: P071 | D21: =[2]Catálogo!F77 -> Abonos, fertilizantes y pesticidas | E21: 81.015396 | F21: =E21/$E$49*100 -> 1.9759837
C22: P073 | D22: =[2]Catálogo!F79 -> Jabón, preparados de limpieza, perfumes y preparados de toilet | E22: 6.6480512 | F22: =E22/$E$49*100 -> 0.16214746
C23: P074 | D23: =[2]Catálogo!F80 -> Otros productos químicos | E23: 0.3690561 | F23: =E23/$E$49*100 -> 0.0090013614
C24: P075 | D24: =[2]Catálogo!F81 -> Productos farmacéuticos | E24: 555.24384 | F24: =E24/$E$49*100 -> 13.542522
C25: P084 | D25: =[2]Catálogo!F90 -> Otros productos elaborados de metal | E25: 9.7954063 | F25: =E25/$E$49*100 -> 0.23891216
C26: P091 | D26: =[2]Catálogo!F97 -> Equipo de transporte | E26: 7.9778743 | F26: =E26/$E$49*100 -> 0.19458215
C27: P093 | D27: =[2]Catálogo!F99 -> Otros artículos n.c.p. | E27: 21.251734 | F27: =E27/$E$49*100 -> 0.51833456
C28: P094 | D28: =[2]Catálogo!F100 -> Residuos y desechos | E28: 515.96369 | F28: =E28/$E$49*100 -> 12.58447
C29: P095 | D29: =[2]Catálogo!F101 -> Generación y distribución de energía eléctrica, gas, vapor y aire acondicionado | E29: 28.334796 | F29: =E29/$E$49*100 -> 0.69109205
C30: P096 | D30: =[2]Catálogo!F102 -> Agua natural y distribución de agua natural | E30: 7.1397384 | F30: =E30/$E$49*100 -> 0.17413982
C31: P101 | D31: =[2]Catálogo!F107 -> Servicios generales y especializados de construcción | E31: 29.58536 | F31: =E31/$E$49*100 -> 0.72159357
C32: P103 | D32: =[2]Catálogo!F109 -> Mantenimiento y reparación de vehículos automotores y motocicletas | E32: 5.3559498 | F32: =E32/$E$49*100 -> 0.13063282
C33: P105 | D33: =[2]Catálogo!F111 -> Servicio de transporte de carga por vía terrestre | E33: 7.3488775 | F33: =E33/$E$49*100 -> 0.17924077
C34: P110 | D34: =[2]Catálogo!F116 -> Servicio de alojamiento | E34: 1.6734592 | F34: =E34/$E$49*100 -> 0.040816045
C35: P111 | D35: =[2]Catálogo!F117 -> Servicio de suministro de comidas y bebidas | E35: 2.7970873 | F35: =E35/$E$49*100 -> 0.068221587
C36: P112 | D36: =[2]Catálogo!F118 -> Servicios de información, telecomunicaciones y radiodifusión | E36: 11.788413 | F36: =E36/$E$49*100 -> 0.28752204
C37: P114 | D37: =[2]Catálogo!F120 -> Otros servicios financieros y servicios de banca de inversión | E37: 1.2705212 | F37: =E37/$E$49*100 -> 0.030988297
C38: P115 | D38: =[2]Catálogo!F121 -> Servicios de Intermediación Financiera Medidos Indirectamente (SIFMI) | E38: 53.071997 | F38: =E38/$E$49*100 -> 1.2944379
C39: P116 | D39: =[2]Catálogo!F122 -> Servicios de seguro, reaseguro y fondos de pensiones | E39: 2.604242 | F39: =E39/$E$49*100 -> 0.063518047
C40: P119 | D40: =[2]Catálogo!F125 -> Otros servicios inmobiliarios, excepto alquiler de vivienda | E40: 4.4253514 | F40: =E40/$E$49*100 -> 0.10793532
C41: P120 | D41: =[2]Catálogo!F126 -> Servicios jurídicos, de contabilidad, auditoría, teneduría de libros y consultoría fiscal | E41: 33.126804 | F41: =E41/$E$49*100 -> 0.80797019
C42: P123 | D42: =[2]Catálogo!F129 -> Otros servicios profesionales, científicos y técnicos | E42: 76.583302 | F42: =E42/$E$49*100 -> 1.8678839
C43: P125 | D43: =[2]Catálogo!F131 -> Servicios de arrendamiento o alquiler sin operador | E43: 12.800119 | F43: =E43/$E$49*100 -> 0.31219778
C44: P126 | D44: =[2]Catálogo!F132 -> Servicios de agencias de empleo y de dotación de recursos humanos | E44: 2.4664604 | F44: =E44/$E$49*100 -> 0.060157523
C45: P128 | D45: =[2]Catálogo!F134 -> Servicios de seguridad, sistemas de seguridad e investigación privada | E45: 23.883323 | F45: =E45/$E$49*100 -> 0.58251961
C46: P132 | D46: =[2]Catálogo!F138 -> Servicios de mantenimiento, reparación e instalación de productos metálicos elaborados, maquinaria y equipo | E46: 16.158635 | F46: =E46/$E$49*100 -> 0.39411274
C47: P134 | D47: =[2]Catálogo!F140 -> Servicios de apoyo a la agricultura, caza, silvicultura y pesca | E47: 6.1775737 | F47: =E47/$E$49*100 -> 0.15067241
C48: P147 | D48: =[2]Catálogo!F153 -> Servicios de asociaciones que sirven a las empresas | E48: 33.956056 | F48: =E48/$E$49*100 -> 0.82819583
B49: Total | E49: =SUBTOTAL(9,E10:E48) -> 4100.0032 | F49: =SUM(F10:F48) -> 100
B53: Tabla 2
B54: Guatemala: Cría de ganado bovino, excepto búfalos
B55: Cuadrante de la demanda del COU
B56: Millones de quetzales y porcentaje
B57: Año 2023 p/
B59: Ranking | C59: Código NPG 2/ | D59: Producto | E59: Monto | F59: Participación (%)
B60: 1 | C60: P054 | D60: Preparados para alimentación animal | E60: 1504.0161 | F60: =E60/$E$70*100 -> 40.024545
B61: =B60+1 -> 2 | C61: P011 | D61: Tabaco y otras plantas no perennes | E61: 762.91318 | F61: =E61/$E$70*100 -> 20.302478
B62: =B61+1 -> 3 | C62: P075 | D62: Productos farmacéuticos | E62: 555.24384 | F62: =E62/$E$70*100 -> 14.776027
B63: =B62+1 -> 4 | C63: P094 | D63: Residuos y desechos | E63: 515.96369 | F63: =E63/$E$70*100 -> 13.730712
B64: =B63+1 -> 5 | C64: P026 | D64: Otros productos de animales vivos | E64: 81.884613 | F64: =E64/$E$70*100 -> 2.1790953
B65: =B64+1 -> 6 | C65: P071 | D65: Abonos, fertilizantes y pesticidas | E65: 81.015396 | F65: =E65/$E$70*100 -> 2.1559639
B66: =B65+1 -> 7 | C66: P123 | D66: Otros servicios profesionales, científicos y técnicos | E66: 76.583302 | F66: =E66/$E$70*100 -> 2.038018
B67: =B66+1 -> 8 | C67: P052 | D67: Azúcar de caña sin refinar y refinada, melaza y los demás azúcares n.c.p. | E67: 66.707651 | F67: =E67/$E$70*100 -> 1.7752093
B68: =B67+1 -> 9 | C68: P068 | D68: Gasolinas, diésel oil y fuel oils | E68: 60.334588 | F68: =E68/$E$70*100 -> 1.6056108
B69: =B68+1 -> 10 | C69: P115 | D69: Servicios de Intermediación Financiera Medidos Indirectamente (SIFMI) | E69: 53.071997 | F69: =E69/$E$70*100 -> 1.4123403
B70: Total | E70: =SUBTOTAL(9,E60:E69) -> 3757.7343 | F70: =E70/'[2] Ganado bovino (3)'!L48*100 -> 44.758795
B71: Fuente: Elaboración propia a partir de datos del Banco de Guatemala
B72: 2/ Nomenclatura de Productos para Guatemala
B73: p/ Cifras preliminares

Sheet Agua
B2: Activdad | C2: AE001 | D2: AE002 | E2: AE003 | F2: AE004 | G2: AE005 | H2: AE006 | I2: AE007 | J2: AE008 | K2: AE009 | L2: AE010 | M2: AE011 | N2: AE012 | O2: AE013 | P2: AE014 | Q2: AE015 | R2: AE016 | S2: AE017 | T2: AE018 | U2: AE019 | V2: AE020 | W2: AE021 | X2: AE022 | Y2: AE023 | Z2: AE024 | AA2: AE025 | AB2: AE026 | AC2: AE027 | AD2: AE028 | AE2: AE029 | AF2: AE030 | AG2: AE031 | AH2: AE032 | AI2: AE033 | AJ2: AE034 | AK2: AE035 | AL2: AE036 | AM2: AE037 | AN2: AE038 | AO2: AE039 | AP2: AE040 | AQ2: AE041 | AR2: AE042 | AS2: AE043 | AT2: AE044 | AU2: AE045 | AV2: AE046 | AW2: AE047 | AX2: AE048 | AY2: AE049 | AZ2: AE050 | BA2: AE051 | BB2: AE052 | BC2: AE053 | BD2: AE054 | BE2: AE055 | BF2: AE056 | BG2: AE057 | BH2: AE058 | BI2: AE059 | BJ2: AE060 | BK2: AE061 | BL2: AE062 | BM2: AE063 | BN2: AE064 | BO2: AE065 | BP2: AE066 | BQ2: AE067 | BR2: AE068 | BS2: AE069 | BT2: AE070 | BU2: AE071 | BV2: AE072 | BW2: AE073 | BX2: AE074 | BY2: AE075 | BZ2: AE076 | CA2: AE077 | CB2: AE078 | CC2: AE079 | CD2: AE080 | CE2: AE081 | CF2: AE082 | CG2: AE083 | CH2: AE084 | CI2: AE085 | CJ2: AE086 | CK2: AE087 | CL2: AE088 | CM2: AE089 | CN2: AE090 | CO2: AE091 | CP2: AE092 | CQ2: AE093 | CR2: AE094 | CS2: AE095 | CT2: AE096 | CU2: AE097 | CV2: AE098 | CW2: AE099 | CX2: AE100 | CY2: AE101 | CZ2: AE102 | DA2: AE103 | DB2: AE104 | DC2: AE105
B3: Monto | C3: 51.487314 | D3: 14.258997 | E3: 78.064738 | F3: 330.30203 | G3: 253.32932 | H3: 28.469492 | I3: 30.086073 | J3: 42.077999 | K3: 25.583063 | L3: 18.219162 | M3: 15.214079 | N3: 7.1397384 | O3: 10.489244 | P3: 15.050831 | Q3: 11.532086 | R3: 0.54023307 | S3: 3.1242418 | T3: 0.60051401 | U3: 0.80705185 | V3: 22.984803 | W3: 21.525146 | X3: 6.4297391 | Y3: 22.934852 | Z3: 1.2476005 | AA3: 28.989943 | AB3: 21.286718 | AC3: 11.440301 | AD3: 3.3653636 | AE3: 1.4713738 | AF3: 86.148028 | AG3: 23.722607 | AH3: 17.974927 | AI3: 70.550978 | AJ3: 44.811411 | AK3: 1.7380122 | AL3: 13.702894 | AM3: 116.01324 | AN3: 31.771429 | AO3: 29.839455 | AP3: 12.044589 | AQ3: 2.3724147 | AR3: 23.080702 | AS3: 7.0224366 | AT3: 2.1028956 | AU3: 23.792384 | AV3: 13.12674 | AW3: 8.7909012 | AX3: 57.561705 | AY3: 0.34862831 | AZ3: 44.961784 | BA3: 17.182033 | BB3: 44.752119 | BC3: 14.770712 | BD3: 31.183848 | BE3: 13.776234 | BF3: 44.009845 | BG3: 51.865408 | BH3: 78.982258 | BI3: 2.5334135 | BJ3: 8.6174158 | BK3: 527.27633 | BL3: 61.18054 | BM3: 98.418696 | BN3: 29.239459 | BO3: 5.4853486 | BP3: 47.989958 | BQ3: 238.30696 | BR3: 5.8085856 | BS3: 15.157627 | BT3: 8.0561349 | BU3: 39.466937 | BV3: 0.73621871 | BW3: 4.906758 | BX3: 0 | BY3: 147.46661 | BZ3: 11.614919 | CA3: 27.005649 | CB3: 5.5544896 | CC3: 32.890457 | CD3: 6.5421822 | CE3: 14.487085 | CF3: 9.1409565 | CG3: 1.6700166 | CH3: 8.7806024 | CI3: 34.952065 | CJ3: 27.855656 | CK3: 36.061876 | CL3: 23.124195 | CM3: 50.590643 | CN3: 39.172824 | CO3: 20.919709 | CP3: 39.420465 | CQ3: 30.364091 | CR3: 0.13183491 | CS3: 0 | CT3: 0 | CU3: 0.15571467 | CV3: 330.66804 | CW3: 9.2675189 | CX3: 25.978852 | CY3: 41.16041 | CZ3: 7.4315195 | DA3: 5.3150561 | DB3: 1.1011282 | DC3: 6.9391994
B5: Actividad | C5: Monto
B6: =[2]Catálogo!C68 -> Comercio al por mayor y al por menor | C6: 527.27633
B7: =[2]Catálogo!C107 -> Administración pública y defensa, excepto planes de seguridad social de afiliación obligatoria (no de mercado) | C7: 330.66804
B8: =[2]Catálogo!C11 -> Cultivo de caña de azúcar | C8: 330.30203
B9: =[2]Catálogo!C12 -> Cultivo de banano y plátano | C9: 253.32932
B10: =[2]Catálogo!C74 -> Actividades de servicio de comidas y bebidas | C10: 238.30696
B11: =[2]Catálogo!C82 -> Alquileres no residenciales y otras actividades inmobiliarias | C11: 147.46661
B12: =[2]Catálogo!C44 -> Elaboración de bebidas no alcohólicas, producción de aguas minerales y de otras aguas embotelladas | C12: 116.01324
B13: =[2]Catálogo!C70 -> Servicios de transporte | C13: 98.418696
B14: =[2]Catálogo!C37 -> Elaboración de almidones y de otros productos de molinería n.c.p. | C14: 86.148028
B15: =[2]Catálogo!C65 -> Construcción de edificios (de mercado) | C15: 78.982258
B16: =[2]Catálogo!C10 -> Cultivo de hortalizas, melones, raíces y tubérculos | C16: 78.064738
B17: =[2]Catálogo!C40 -> Elaboración de azúcar | C17: 70.550978
B18: =[2]Catálogo!C69 -> Mantenimiento y reparación de vehículos automotores y motocicletas | C18: 61.18054
B19: =[2]Catálogo!C55 -> Fabricación de plásticos en forma primaria y productos de caucho y plástico | C19: 57.561705
B20: =[2]Catálogo!C64 -> Suministro de agua, evacuación de aguas residuales, gestión de desechos y descontaminación | C20: 51.865408
B21: =[2]Catálogo!C8 -> Cultivo de cereales | C21: 51.487314
B22: =[2]Catálogo!C96 -> Actividades de médicos y odontólogos (de mercado) | C22: 50.590643
B23: =[2]Catálogo!C73 -> Actividades de alojamiento | C23: 47.989958
B24: =[2]Catálogo!C57 -> Fabricación de cemento, cal y yeso; y fabricación de artículos de hormigón, cemento y yeso | C24: 44.961784
B25: =[2]Catálogo!C41 -> Elaboración de otros productos alimenticios n.c.p | C25: 44.811411
B26: =[2]Catálogo!C59 -> Fabricación de metales comunes y de productos elaborados de metal, excepto maquinaria y equipo | C26: 44.752119
B27: =[2]Catálogo!C63 -> Suministro de electricidad, gas, vapor y aire acondicionado | C27: 44.009845
B28: =[2]Catálogo!C15 -> Cultivo de café | C28: 42.077999
B29: =[2]Catálogo!C110 -> Actividades de hospitales (no de mercado) | C29: 41.16041
B30: =[2]Catálogo!C78 -> Actividades de servicios financieros, excepto las de seguros y fondos de pensiones | C30: 39.466937
B31: =[2]Catálogo!C99 -> Otras actividades de servicios | C31: 39.420465
B32: =[2]Catálogo!C97 -> Otras actividades de atención de la salud humana (de mercado) | C32: 39.172824
B33: =[2]Catálogo!C94 -> Enseñanza (de mercado) | C33: 36.061876
B34: =[2]Catálogo!C92 -> Actividades de centros de llamadas | C34: 34.952065
B35: =[2]Catálogo!C86 -> Publicidad y estudios de mercado | C35: 32.890457
B36: =[2]Catálogo!C45 -> Hilatura, tejedura y fabricación de productos textiles, excepto prendas de vestir | C36: 31.771429
B37: =[2]Catálogo!C61 -> Fabricación de muebles | C37: 31.183848
B38: =[2]Catálogo!C101 -> Construcción de edificios (para uso final propio) | C38: 30.364091
B39: =[2]Catálogo!C14 -> Cultivo de palma | C39: 30.086073
B40: =[2]Catálogo!C46 -> Fabricación de prendas de vestir | C40: 29.839455
B41: =[2]Catálogo!C71 -> Almacenamiento y actividades de apoyo al transporte | C41: 29.239459
B42: =[2]Catálogo!C32 -> Elaboración y conservación de frutas, legumbres y hortalizas | C42: 28.989943
B43: =[2]Catálogo!C13 -> Cultivo de otras frutas y nueces | C43: 28.469492
B44: =[2]Catálogo!C93 -> Otras actividades de servicios administrativos y de apoyo de oficina | C44: 27.855656
B45: =[2]Catálogo!C84 -> Actividades de oficinas principales y actividades de consultoría de gestión | C45: 27.005649
B46: =[2]Catálogo!C109 -> Enseñanza (no de mercado) | C46: 25.978852
B47: =[2]Catálogo!C16 -> Cultivo de cardamomo | C47: 25.583063
B48: =[2]Catálogo!C52 -> Fabricación de jabones y detergentes, preparados para limpiar y pulir, perfumes y preparados de tocador | C48: 23.792384
B49: =[2]Catálogo!C38 -> Elaboración de productos de panadería | C49: 23.722607
B50: =[2]Catálogo!C95 -> Actividades de hospitales (de mercado) | C50: 23.124195
B51: =[2]Catálogo!C49 -> Fabricación de papel y productos de papel | C51: 23.080702
B52: =[2]Catálogo!C27 -> Extracción de minerales no metálicos y actividades de apoyo para la explotación de minas y canteras | C52: 22.984803
B53: =[2]Catálogo!C30 -> Elaboración y conservación de carne de aves de corral | C53: 22.934852
B54: =[2]Catálogo!C28 -> Elaboración y conservación de carne de ganado bovino | C54: 21.525146
B55: =[2]Catálogo!C33 -> Elaboración de aceites y grasas de origen vegetal y animal | C55: 21.286718
B56: =[2]Catálogo!C98 -> Actividades artísticas, de entretenimiento y recreativas (de mercado) | C56: 20.919709
B57: =[2]Catálogo!C17 -> Cultivo de caucho natural | C57: 18.219162
B58: =[2]Catálogo!C39 -> Elaboración de tortillas de maíz | C58: 17.974927
B59: =[2]Catálogo!C58 -> Fabricación de otros productos minerales no metálicos | C59: 17.182033
B60: =[2]Catálogo!C18 -> Otros cultivos | C60: 15.214079
B61: =[2]Catálogo!C76 -> Telecomunicaciones | C61: 15.157627
B62: =[2]Catálogo!C21 -> Cría de ganado porcino, de otros animales y obtención de productos de otros animales vivos | C62: 15.050831
B63: =[2]Catálogo!C60 -> Fabricación, reparación e instalación de maquinaria y equipo industrial, n.c.p. | C63: 14.770712
B64: =[2]Catálogo!C88 -> Actividades de alquiler y arrendamiento | C64: 14.487085
B65: =[2]Catálogo!C9 -> Cultivo de leguminosas (legumbres secas) y semillas oleaginosas | C65: 14.258997
B66: =[2]Catálogo!C62 -> Otras industrias manufactureras | C66: 13.776234
B67: =[2]Catálogo!C43 -> Elaboración de bebidas alcohólicas y productos de tabaco | C67: 13.702894
B68: =[2]Catálogo!C53 -> Fabricación de productos farmacéuticos, sustancias químicas medicinales y productos botánicos de uso farmacéutico | C68: 13.12674
B69: =[2]Catálogo!C47 -> Fabricación de calzado, productos de cuero y actividades conexas | C69: 12.044589
B70: =[2]Catálogo!C83 -> Actividades jurídicas y de contabilidad | C70: 11.614919
B71: =[2]Catálogo!C22 -> Actividades de apoyo a la agricultura y ganadería; y propagación de plantas | C71: 11.532086
B72: =[2]Catálogo!C34 -> Elaboración de productos lácteos | C72: 11.440301
B73: =[2]Catálogo!C20 -> Cría de aves de corral | C73: 10.489244
B74: =[2]Catálogo!C108 -> Actividades de planes de seguridad social de afiliación obligatoria (no de mercado) | C74: 9.2675189
B75: =[2]Catálogo!C89 -> Actividades de empleo | C75: 9.1409565
B76: =[2]Catálogo!C54 -> Fabricación de otros productos químicos, coque y productos de la refinación del petróleo | C76: 8.7909012
B77: =[2]Catálogo!C91 -> Actividades de seguridad, investigación privada y de detectives | C77: 8.7806024
B78: =[2]Catálogo!C67 -> Actividades especializadas de construcción | C78: 8.6174158
B79: =[2]Catálogo!C77 -> Programación informática, consultoría de informática y actividades conexas; actividades de servicios de información; y edición de programas informáticos | C79: 8.0561349
B80: =[2]Catálogo!C111 -> Actividades de médicos y odontólogos (no de mercado) | C80: 7.4315195
B81: =[2]Catálogo!C19 -> Cría de ganado bovino, excepto búfalos | C81: 7.1397384
B82: =[2]Catálogo!C50 -> Impresión y reproducción de grabaciones | C82: 7.0224366
B83: =[2]Catálogo!C114 -> Actividades de asociaciones que sirven a los hogares (no de mercado) | C83: 6.9391994
B84: =[2]Catálogo!C87 -> Investigación y desarrollo (de mercado); otras actividades profesionales, científicas y técnicas; y actividades veterinarias | C84: 6.5421822
B85: =[2]Catálogo!C29 -> Elaboración y conservación de carne de ganado porcino, productos cárnicos y otros productos de origen animal n.c.p. | C85: 6.4297391
B86: =[2]Catálogo!C75 -> Edición de libros y otras actividades de edición; actividades de producción de películas cinematográficas, videos y programas de televisión | C86: 5.8085856
B87: =[2]Catálogo!C85 -> Actividades de arquitectura e ingeniería, ensayos y análisis técnicos | C87: 5.5544896
B88: =[2]Catálogo!C72 -> Actividades postales y de mensajería | C88: 5.4853486
B89: =[2]Catálogo!C112 -> Otras actividades de atención de la salud humana (no de mercado) | C89: 5.3150561
B90: =[2]Catálogo!C80 -> Actividades auxiliares de las actividades de servicios financieros | C90: 4.906758
B91: =[2]Catálogo!C35 -> Elaboración de harina de trigo | C91: 3.3653636
B92: =[2]Catálogo!C24 -> Pesca y acuicultura | C92: 3.1242418
B93: =[2]Catálogo!C66 -> Construcción de obras de ingeniería civil (de mercado) | C93: 2.5334135
B94: =[2]Catálogo!C48 -> Aserrado y acepilladura de madera, fabricación de productos de madera y corcho, excepto muebles | C94: 2.3724147
B95: =[2]Catálogo!C51 -> Fabricación de abonos, compuestos de nitrógeno, plaguicidas y otros productos químicos de uso agropecuario | C95: 2.1028956
B96: =[2]Catálogo!C42 -> Elaboración de alimentos preparados para animales | C96: 1.7380122
B97: =[2]Catálogo!C90 -> Actividades de agencias de viajes, operadores turísticos, servicios de reservas y actividades conexas | C97: 1.6700166
B98: =[2]Catálogo!C36 -> Beneficios de arroz | C98: 1.4713738
B99: =[2]Catálogo!C31 -> Elaboración y conservación de pescado, crustáceos y moluscos | C99: 1.2476005
B100: =[2]Catálogo!C113 -> Actividades artísticas, de entretenimiento y recreativas (no de mercado) | C100: 1.1011282
B101: =[2]Catálogo!C26 -> Extracción de minerales metálicos | C101: 0.80705185
B102: =[2]Catálogo!C79 -> Seguros, reaseguros y fondos de pensiones, excepto planes de seguridad social de afiliación obligatoria | C102: 0.73621871
...
